ckanext_csvwmapandtransform-1.0.2-py3.13-nspkg.pth
ckanext/csvwmapandtransform/__init__.py
ckanext/csvwmapandtransform/action.py
ckanext/csvwmapandtransform/auth.py
ckanext/csvwmapandtransform/cli.py
ckanext/csvwmapandtransform/db.py
ckanext/csvwmapandtransform/helpers.py
ckanext/csvwmapandtransform/mapper.py
ckanext/csvwmapandtransform/plugin.py
ckanext/csvwmapandtransform/tasks.py
ckanext/csvwmapandtransform/views.py
ckanext/csvwmapandtransform/assets/script.js
ckanext/csvwmapandtransform/assets/style.css
ckanext/csvwmapandtransform/assets/webassets.yml
ckanext/csvwmapandtransform/i18n/de/LC_MESSAGES/ckanext-csvwmapandtransform.mo
ckanext/csvwmapandtransform/templates/csvwmapandtransform/create_mapping.html
ckanext/csvwmapandtransform/templates/csvwmapandtransform/transform.html
ckanext/csvwmapandtransform/templates/package/resource_read.html
ckanext/csvwmapandtransform/templates/package/snippets/resource_item.html
ckanext/csvwmapandtransform/tests/__init__.py
ckanext_csvwmapandtransform-1.0.2.dist-info/licenses/LICENSE
ckanext_csvwmapandtransform-1.0.2.dist-info/METADATA
ckanext_csvwmapandtransform-1.0.2.dist-info/WHEEL
ckanext_csvwmapandtransform-1.0.2.dist-info/entry_points.txt
ckanext_csvwmapandtransform-1.0.2.dist-info/namespace_packages.txt
ckanext_csvwmapandtransform-1.0.2.dist-info/top_level.txt
ckanext_csvwmapandtransform-1.0.2.dist-info/RECORD
